{"node_id": "156993ff170c50028650dce990cce372", "title": "Particular solutions to differential equations", "description": "Practice finding what that little \"+c\" should be when your integral is used for a real problem.", "topic_path": ["Khan Academy (English - US curriculum)", "Math", "AP®︎ Calculus BC", "Differential equations", "Finding particular solutions using initial conditions and separation of variables", "Particular solutions to differential equations"], "assessment_items": [{"item_id": "08ba9738b3495f3fa24d7b5c82afc8e6", "question_content": "**$f\\,^{\\prime}(x)=12x^2-6x+2$ and $f(-1)=3$.** \n\n$f(2) = $ [[☃ numeric-input 1]]", "hints": ["##Finding $f(x)$\n\nWe have $f'(x)=12x^2-6x+2$ and we want to find $f(x)$:\n\n$\\begin{align}f(x) &= \\displaystyle \\int f'(x)\\,dx\n\\\\\\\\\n& = \\displaystyle \\int (12x^2-6x+2)\\,dx\n\\\\\\\\\n& =  \\blueD{4x^3-3x^2+2x} \\maroonD{+ C}\n\\end{align}$", "##Finding $\\maroonD C$\n\n**Goal:** We need to find $\\maroonD C$ such that $f(-1)=3$. \n\nHere's what we get when we plug in $-1$:\n\n$\\begin{align}f(-1)&=\\blueD{4(-1)^3-3(-1)^2+2(-1)} \\maroonD{+ C}\\\\\\\\\n&=\\blueD{-9} \\maroonD{+ C} \n\\end{align}$ \n\nWe are given that this must equal $3$:\n\n$3 = \\blueD{-9} \\maroonD{+ C}$\n\nSolving the equation gives us $\\maroonD{C=12}$. ", "##Finding $f(2)$\n\nNow, we have that $f(x)=\\blueD{4x^3-3x^2+2x} \\maroonD{+12}$. \n\nLet's find $f(2)$ by plugging in $2$:\n\n$\\begin{align}f(2)&=4(2)^3-3(2)^2+2(2) + 12\\\\\\\\\n&=36\n\\end{align}$ ", "##The answer\n\n$f(2) = 36$"], "widget_types": ["numeric-input"], "answer_data": {"numeric-input 1": {"type": "numeric-input", "answers": [{"maxError": null, "message": "", "simplify": "required", "status": "correct", "strict": false, "value": 36}]}}}, {"item_id": "a7e35b216276550eb7c1a7553ec03bf2", "question_content": "**$f\\,^{\\prime}(x)=-3x^2+2x+4$ and $f(4)=-20$.** \n\n$f(2) = $ [[☃ numeric-input 1]]", "hints": ["##Finding $f(x)$\n\nWe have $f'(x)=-3x^2+2x+4$ and we want to find $f(x)$:\n\n$\\begin{align}f(x) &= \\displaystyle \\int f'(x)\\,dx\n\\\\\\\\\n& = \\displaystyle \\int (-3x^2+2x+4)\\,dx\n\\\\\\\\\n& =  \\blueD{-x^3+x^2+4x} \\maroonD{+ C}\n\\end{align}$", "##Finding $\\maroonD C$\n\n**Goal:** We need to find $\\maroonD C$ such that $f(4)=-20$. \n\nHere's what we get when we plug in $4$:\n\n$\\begin{align}f(4)&=\\blueD{-(4)^3+(4)^2+4(4)} \\maroonD{+ C}\\\\\\\\\n&=\\blueD{-32} \\maroonD{+ C} \n\\end{align}$ \n\nWe are given that this must equal $-20$:\n\n$-20 = \\blueD{-32} \\maroonD{+ C}$\n\nSolving the equation gives us $\\maroonD{C=12}$. ", "##Finding $f(2)$\n\nNow, we have that $f(x)=\\blueD{-x^3+x^2+4x} \\maroonD{+12}$. \n\nLet's find $f(2)$ by plugging in $2$:\n\n$\\begin{align}f(2)&=-(2)^3+(2)^2+4(2) + 12\\\\\\\\\n&=16\n\\end{align}$ ", "##The answer\n\n$f(2) = 16$"], "widget_types": ["numeric-input"], "answer_data": {"numeric-input 1": {"type": "numeric-input", "answers": [{"maxError": null, "message": "", "simplify": "required", "status": "correct", "strict": false, "value": 16}]}}}, {"item_id": "7af2726556cc57b79da58ed9df86465b", "question_content": "**$f\\,^{\\prime}(x)=8x^3-12x$ and $f(1)=1$.** \n\n$f(-2) = $ [[☃ numeric-input 1]]", "hints": ["##Finding $f(x)$\n\nWe have $f'(x)=8x^3-12x$ and we want to find $f(x)$:\n\n$\\begin{align}f(x) &= \\displaystyle \\int f'(x)\\,dx\n\\\\\\\\\n&= \\displaystyle \\int (8x^3-12x)\\,dx\n\\\\\\\\\n& =  \\blueD{2x^4-6x^2} \\maroonD{+ C}\n\\end{align}$", "##Finding $\\maroonD C$\n\n**Goal:** We need to find $\\maroonD C$ such that $f(1)=1$. \n\nHere's what we get when we plug in $1$:\n\n$\\begin{align}f(1)&=\\blueD{2(1)^4-6(1)^2} \\maroonD{+ C}\\\\\\\\\n&=\\blueD{-4} \\maroonD{+ C} \n\\end{align}$ \n\nWe are given that this must equal $1$:\n\n$1 = \\blueD{-4} \\maroonD{+ C}$\n\nSolving the equation gives us $\\maroonD{C=5}$. ", "##Finding $f(-2)$\n\nNow, we have that $f(x)=\\blueD{2x^4-6x^2} \\maroonD{+5}$. \n\nLet's find $f(-2)$ by plugging in $-2$:\n\n$\\begin{align}f(-2)&=2(-2)^4-6(-2)^2+5\\\\\\\\\n&=13\n\\end{align}$ ", "##The answer\n\n$f(-2) = 13$"], "widget_types": ["numeric-input"], "answer_data": {"numeric-input 1": {"type": "numeric-input", "answers": [{"maxError": null, "message": "", "simplify": "required", "status": "correct", "strict": false, "value": 13}]}}}, {"item_id": "ce4107d443c35b2986342e91560c46e1", "question_content": "**$f\\,^{\\prime}(x)=6x^5+7$ and $f(-2)=30$.** \n\n$f(1) = $ [[☃ numeric-input 1]]", "hints": ["##Finding $f(x)$\n\nWe have $f'(x)=6x^5+7$ and we want to find $f(x)$:\n\n$\\begin{align}f(x) &= \\displaystyle \\int f'(x)\\,dx\n\\\\\\\\\n&= \\displaystyle \\int (6x^5+7)\\,dx\n\\\\\\\\\n& =  \\blueD{x^6+7x} \\maroonD{+ C}\n\\end{align}$", "##Finding $\\maroonD C$\n\n**Goal:** We need to find $\\maroonD C$ such that $f(-2)=30$. \n\nHere's what we get when we plug in $-2$:\n\n$\\begin{align}f(-2)&=\\blueD{(-2)^6+7(-2)} \\maroonD{+ C}\\\\\\\\\n&=\\blueD{50} \\maroonD{+ C}\n\\end{align}$ \n\nWe are given that this must equal $30$:\n\n$30 = \\blueD{50} \\maroonD{+ C}$\n\nSolving the equation gives us $\\maroonD{C=-20}$. ", "##Finding $f(1)$\n\nNow, we have that $f(x)=\\blueD{x^6+7x} \\maroonD{-20}$. \n\nLet's find $f(1)$ by plugging in $1$:\n\n$\\begin{align}f(1)&=(1)^6+7(1) - 20\\\\\\\\\n&=-12\n\\end{align}$ ", "##The answer\n\n$f(1) = -12$"], "widget_types": ["numeric-input"], "answer_data": {"numeric-input 1": {"type": "numeric-input", "answers": [{"maxError": null, "message": "", "simplify": "required", "status": "correct", "strict": false, "value": -12}]}}}, {"item_id": "f2dcbf1352475c8e981648d50d797216", "question_content": "**$f\\,^{\\prime}(x)=-5x^4+9x^2$ and $f(3)=-80$.** \n\n$f(-3) = $ [[☃ numeric-input 1]]", "hints": ["##Finding $f(x)$\n\nWe have $f'(x)=-5x^4+9x^2$ and we want to find $f(x)$:\n\n$\\begin{align}f(x) &= \\displaystyle \\int f'(x)\\,dx\n\\\\\\\\\n& = \\displaystyle \\int (-5x^4+9x^2)\\,dx\n\\\\\\\\\n& =  \\blueD{-x^5+3x^3} \\maroonD{+ C}\n\\end{align}$", "##Finding $\\maroonD C$\n\n**Goal:** We need to find $\\maroonD C$ such that $f(3)=-80$. \n\nHere's what we get when we plug in $3$:\n\n$\\begin{align}f(3)&=\\blueD{-(3)^5+3(3)^3} \\maroonD{+ C}\\\\\\\\\n&=\\blueD{-162} \\maroonD{+ C} \n\\end{align}$ \n\nWe are given that this must equal $-80$:\n\n$-80 = \\blueD{-162} \\maroonD{+ C}$\n\nSolving the equation gives us $\\maroonD{C=82}$. ", "##Finding $f(-3)$\n\nNow, we have that $f(x)=\\blueD{-x^5+3x^3} \\maroonD{+82}$. \n\nLet's find $f(-3)$ by plugging in $-3$:\n\n$\\begin{align}f(-3)&=-(-3)^5+3(-3)^3 + 82\\\\\\\\\n&=244\n\\end{align}$ ", "##The answer\n\n$f(-3) = 244$"], "widget_types": ["numeric-input"], "answer_data": {"numeric-input 1": {"type": "numeric-input", "answers": [{"maxError": null, "message": "", "simplify": "required", "status": "correct", "strict": false, "value": 244}]}}}, {"item_id": "81f031508d75590ea9623adc15ea59cc", "question_content": "**$f\\,^{\\prime}(x)=-10x^4+8x^3$ and $f(1)=9$.** \n\n$f(0) = $ [[☃ numeric-input 1]]", "hints": ["##Finding $f(x)$\n\nWe have $f'(x)=-10x^4+8x^3$ and we want to find $f(x)$:\n\n$\\begin{align}f(x)& = \\displaystyle \\int f'(x)\\,dx\n\\\\\\\\\n& = \\displaystyle \\int (-10x^4+8x^3)\\,dx\n\\\\\\\\\n& =  \\blueD{-2x^5+2x^4} \\maroonD{+ C}\n\\end{align}$", "##Finding $\\maroonD C$\n\n**Goal:** We need to find $\\maroonD C$ such that $f(1)=9$. \n\nHere's what we get when we plug in $1$:\n\n$\\begin{align}f(1)&=\\blueD{-2(1)^5+2(1)^4} \\maroonD{+ C}\\\\\\\\\n&=\\blueD{0} \\maroonD{+ C} \n\\end{align}$ \n\nWe are given that this must equal $9$:\n\n$9 = \\blueD{0} \\maroonD{+ C}$\n\nSolving the equation gives us $\\maroonD{C=9}$. ", "##Finding $f(0)$\n\nNow, we have that $f(x)=\\blueD{-2x^5+2x^4} \\maroonD{+9}$. \n\nLet's find $f(0)$ by plugging in $0$:\n\n$\\begin{align}f(0)&=-2(0)^5+2(0)^4 + 9\\\\\\\\\n&=9\n\\end{align}$ ", "##The answer\n\n$f(0) = 9$"], "widget_types": ["numeric-input"], "answer_data": {"numeric-input 1": {"type": "numeric-input", "answers": [{"maxError": null, "message": "", "simplify": "required", "status": "correct", "strict": false, "value": 9}]}}}, {"item_id": "f7b9b14c726352a9b471ec55c97d0cef", "question_content": "**$f\\,^{\\prime}(x)=3x^2-2x+7$ and $f(6)=200$.** \n\n$f(1) = $ [[☃ numeric-input 1]]", "hints": ["##Finding $f(x)$\n\nWe have $f'(x)=3x^2-2x+7$ and we want to find $f(x)$:\n\n$\\begin{align}f(x) &= \\displaystyle \\int f'(x)\\,dx\n\\\\\\\\\n& = \\displaystyle \\int (3x^2-2x+7)\\,dx\n\\\\\\\\\n& =  \\blueD{x^3-x^2+7x} \\maroonD{+ C}\n\\end{align}$", "##Finding $\\maroonD C$\n\n**Goal:** We need to find $\\maroonD C$ such that $f(6)=200$. \n\nHere's what we get when we plug in $6$:\n\n$\\begin{align}f(6)&=\\blueD{(6)^3-(6)^2+7(6)} \\maroonD{+ C}\\\\\\\\\n&=\\blueD{222} \\maroonD{+ C} \n\\end{align}$ \n\nWe are given that this must equal $200$:\n\n$200 = \\blueD{222} \\maroonD{+ C}$\n\nSolving the equation gives us $\\maroonD{C=-22}$. ", "##Finding $f(1)$\n\nNow, we have that $f(x)=\\blueD{x^3-x^2+7x} \\maroonD{-22}$. \n\nLet's find $f(1)$ by plugging in $1$:\n\n$\\begin{align}f(1)&=(1)^3-(1)^2+7(1) - 22\\\\\\\\\n&=-15\n\\end{align}$ ", "##The answer\n\n$f(1) = -15$"], "widget_types": ["numeric-input"], "answer_data": {"numeric-input 1": {"type": "numeric-input", "answers": [{"maxError": null, "message": "", "simplify": "required", "status": "correct", "strict": false, "value": -15}]}}}, {"item_id": "8255410f745152e5832d542f1461e0e0", "question_content": "**$f\\,^{\\prime}(x)=16x^3+6x-7$ and $f(5)=2500$.** \n\n$f(-1) = $ [[☃ numeric-input 1]]", "hints": ["##Finding $f(x)$\n\nWe have $f'(x)=16x^3+6x-7$ and we want to find $f(x)$:\n\n$\\begin{align}f(x) &= \\displaystyle \\int f'(x)\\,dx\n\\\\\\\\\n& = \\displaystyle \\int (16x^3+6x-7)\\,dx\n\\\\\\\\\n& =  \\blueD{4x^4+3x^2-7x} \\maroonD{+ C}\n\\end{align}$", "##Finding $\\maroonD C$\n\n**Goal:** We need to find $\\maroonD C$ such that $f(5)=2500$. \n\nHere's what we get when we plug in $5$:\n\n$\\begin{align}f(5)&=\\blueD{4(5)^4+3(5)^2-7(5)} \\maroonD{+ C}\\\\\\\\\n&=\\blueD{2540} \\maroonD{+ C}\n\\end{align}$ \n\nWe are given that this must equal $2500$:\n\n$2500 = \\blueD{2540} \\maroonD{+ C}$\n\nSolving the equation gives us $\\maroonD{C=-40}$. ", "##Finding $f(-1)$\n\nNow, we have that $f(x)=\\blueD{4x^4+3x^2-7x} \\maroonD{-40}$. \n\nLet's find $f(-1)$ by plugging in $-1$:\n\n$\\begin{align}f(-1)&=4(-1)^4+3(-1)^2-7(-1) - 40\\\\\\\\\n&=-26\n\\end{align}$ ", "##The answer\n\n$f(-1) = -26$"], "widget_types": ["numeric-input"], "answer_data": {"numeric-input 1": {"type": "numeric-input", "answers": [{"maxError": null, "message": "", "simplify": "required", "status": "correct", "strict": false, "value": -26}]}}}, {"item_id": "8a4bd156c7065e60b22797edb775cd1b", "question_content": "**$f\\,^{\\prime}(x)=-3e^x$ and $f(1)=12-3e$.** \n\n$f(0) = $ [[☃ numeric-input 2]]", "hints": ["##Finding $f(x)$\n\nWe have $f'(x)=-3e^x$ and we want to find $f(x)$:\n\n$\\begin{align}f(x) &= \\displaystyle \\int f'(x)\\,dx\n\\\\\\\\\n& = \\displaystyle \\int (-3e^x)\\,dx\n\\\\\\\\\n& =  \\blueD{-3e^x} \\maroonD{+ C}\n\\end{align}$", "##Finding $\\maroonD C$\n\n**Goal:** We need to find $\\maroonD C$ such that $f(1)=12-3e$. \n\nHere's what we get when we plug in $-1$:\n\n$\\begin{align}f(-1)&=\\blueD{-3e^{1}} \\maroonD{+ C}\\\\\\\\\n&=\\blueD{-3e} \\maroonD{+ C}\n\\end{align}$ \n\nWe are given that this must equal $12-3e$:\n\n$12-3e = \\blueD{-3e} \\maroonD{+ C}$\n\nSolving the equation gives us $\\maroonD{C=12}$. ", "##Finding $f(0)$\n\nNow, we have that $f(x)=\\blueD{-3e^x} \\maroonD{+ 12}$. \n\nLet's find $f(0)$ by plugging in $0$:\n\n$\\begin{align}f(0)&=-3e^0 + 12\\\\\\\\\n&=9\n\\end{align}$ ", "##The answer\n\n$f(0) = 9$"], "widget_types": ["numeric-input"], "answer_data": {"numeric-input 2": {"type": "numeric-input", "answers": [{"maxError": null, "message": "", "simplify": "required", "status": "correct", "strict": false, "value": 9}]}}}, {"item_id": "c133b6c64c4b5dafa382fe2ca44bd10d", "question_content": "**$f\\,^{\\prime}(x)=4e^x$ and $f(2)=16+4e^2$.** \n\n$f(0) = $ [[☃ numeric-input 2]]", "hints": ["##Finding $f(x)$\n\nWe have $f'(x)=4e^x$ and we want to find $f(x)$:\n\n$\\begin{align}f(x) &= \\displaystyle \\int f'(x)\\,dx\n\\\\\\\\\n& = \\displaystyle \\int (4e^x)\\,dx\n\\\\\\\\\n& =  \\blueD{4e^x} \\maroonD{+ C}\n\\end{align}$", "##Finding $\\maroonD C$\n\n**Goal:** We need to find $\\maroonD C$ such that $f(2)=16+4e^2$. \n\nHere's what we get when we plug in $2$:\n\n$\\begin{align}f(2)&=\\blueD{4e^{2}} \\maroonD{+ C}\n\\end{align}$ \n\nWe are given that this must equal $16+4e^2$:\n\n$16+4e^2 = \\blueD{4e^2} \\maroonD{+ C}$\n\nSolving the equation gives us $\\maroonD{C=16}$. ", "##Finding $f(0)$\n\nNow, we have that $f(x)=\\blueD{4e^x} \\maroonD{+ 16}$. \n\nLet's find $f(0)$ by plugging in $0$:\n\n$\\begin{align}f(0)&=4e^0 + 16\\\\\\\\\n&=20\n\\end{align}$ ", "##The answer\n\n$f(0) = 20$"], "widget_types": ["numeric-input"], "answer_data": {"numeric-input 2": {"type": "numeric-input", "answers": [{"maxError": null, "message": "", "simplify": "required", "status": "correct", "strict": false, "value": 20}]}}}, {"item_id": "421d2d9f71235d758fdc32ba424bcf8a", "question_content": "**$f\\,^{\\prime}(x)=-5e^x$ and $f(3)=22-5e^3$.** \n\n$f(0) = $ [[☃ numeric-input 2]]", "hints": ["##Finding $f(x)$\n\nWe have $f'(x)=-5e^x$ and we want to find $f(x)$:\n\n$\\begin{align}f(x) &= \\displaystyle \\int f'(x)\\,dx\n\\\\\\\\\n& = \\displaystyle \\int (-5e^x)\\,dx\n\\\\\\\\\n& =  \\blueD{-5e^x} \\maroonD{+ C}\n\\end{align}$", "##Finding $\\maroonD C$\n\n**Goal:** We need to find $\\maroonD C$ such that $f(3)=22-5e^3$. \n\nHere's what we get when we plug in $3$:\n\n$\\begin{align}f(3)&=\\blueD{-5e^{3}} \\maroonD{+ C}\n\\end{align}$ \n\nWe are given that this must equal $22-5e^3$:\n\n$22-5e^3 = \\blueD{-5e^{3}} \\maroonD{+ C}$\n\nSolving the equation gives us $\\maroonD{C=22}$. ", "##Finding $f(0)$\n\nNow, we have that $f(x)=\\blueD{-5e^x} \\maroonD{+ 22}$. \n\nLet's find $f(0)$ by plugging in $0$:\n\n$\\begin{align}f(0)&=-5e^0 + 22\\\\\\\\\n&=17\n\\end{align}$ ", "##The answer\n\n$f(0) = 17$"], "widget_types": ["numeric-input"], "answer_data": {"numeric-input 2": {"type": "numeric-input", "answers": [{"maxError": null, "message": "", "simplify": "required", "status": "correct", "strict": false, "value": 17}]}}}, {"item_id": "f6f1af71209a5078b9791f14788284b3", "question_content": "**$f\\,^{\\prime}(x)=12e^x$ and $f(4)=-16+12e^4$.** \n\n$f(0) = $ [[☃ numeric-input 2]]", "hints": ["##Finding $f(x)$\n\nWe have $f'(x)=12e^x$ and we want to find $f(x)$:\n\n$\\begin{align}f(x) &= \\displaystyle \\int f'(x)\\,dx\n\\\\\\\\\n& = \\displaystyle \\int (12e^x)\\,dx\n\\\\\\\\\n& =  \\blueD{12e^x} \\maroonD{+ C}\n\\end{align}$", "##Finding $\\maroonD C$\n\n**Goal:** We need to find $\\maroonD C$ such that $f(4)=-16+12e^4$. \n\nHere's what we get when we plug in $4$:\n\n$\\begin{align}f(4)&=\\blueD{12e^{4}} \\maroonD{+ C}\n\\end{align}$ \n\nWe are given that this must equal $-16+12e^4$:\n\n$-16+12e^4 = \\blueD{12e^{4}} \\maroonD{+ C}$\n\nSolving the equation gives us $\\maroonD{C=-16}$. ", "##Finding $f(0)$\n\nNow, we have that $f(x)=\\blueD{12e^x} \\maroonD{-16}$. \n\nLet's find $f(0)$ by plugging in $0$:\n\n$\\begin{align}f(0)&=12e^0 - 16\\\\\\\\\n&=-4\n\\end{align}$ ", "##The answer\n\n$f(0) = -4$"], "widget_types": ["numeric-input"], "answer_data": {"numeric-input 2": {"type": "numeric-input", "answers": [{"maxError": null, "message": "", "simplify": "required", "status": "correct", "strict": false, "value": -4}]}}}, {"item_id": "ced89a19bbe453a8bdee55733f8ea8c5", "question_content": "**$f\\,^{\\prime}(x)=-7e^x$ and $f(5)=24-7e^5$.** \n\n$f(0) = $ [[☃ numeric-input 2]]", "hints": ["##Finding $f(x)$\n\nWe have $f'(x)=-7e^x$ and we want to find $f(x)$:\n\n$\\begin{align}f(x) &= \\displaystyle \\int f'(x)\\,dx\n\\\\\\\\\n& = \\displaystyle \\int (-7e^x)\\,dx\n\\\\\\\\\n& =  \\blueD{-7e^x} \\maroonD{+ C}\n\\end{align}$", "##Finding $\\maroonD C$\n\n**Goal:** We need to find $\\maroonD C$ such that $f(5)=24-7e^5$. \n\nHere's what we get when we plug in $5$:\n\n$\\begin{align}f(5)&=\\blueD{-7e^{5}} \\maroonD{+ C}\n\\end{align}$ \n\nWe are given that this must equal $24-7e^5$:\n\n$24-7e^5 = \\blueD{-7e^{5}} \\maroonD{+ C}$\n\nSolving the equation gives us $\\maroonD{C=24}$. ", "##Finding $f(0)$\n\nNow, we have that $f(x)=\\blueD{-7e^x} \\maroonD{+ 24}$. \n\nLet's find $f(0)$ by plugging in $0$:\n\n$\\begin{align}f(0)&=-7e^0 + 24\\\\\\\\\n&=17\n\\end{align}$ ", "##The answer\n\n$f(0) = 17$"], "widget_types": ["numeric-input"], "answer_data": {"numeric-input 2": {"type": "numeric-input", "answers": [{"maxError": null, "message": "", "simplify": "required", "status": "correct", "strict": false, "value": 17}]}}}, {"item_id": "a57f264002565c25b5e72fd9d86947b8", "question_content": "**$f\\,^{\\prime}(x)=-27e^x$ and $f(6)=36-27e^6$.** \n\n$f(0) = $ [[☃ numeric-input 2]]", "hints": ["##Finding $f(x)$\n\nWe have $f'(x)=-27e^x$ and we want to find $f(x)$:\n\n$\\begin{align}f(x) &= \\displaystyle \\int f'(x)\\,dx\n\\\\\\\\\n& = \\displaystyle \\int (-27e^x)\\,dx\n\\\\\\\\\n& =  \\blueD{-27e^x} \\maroonD{+ C}\n\\end{align}$", "##Finding $\\maroonD C$\n\n**Goal:** We need to find $\\maroonD C$ such that $f(6)=36-27e^6$. \n\nHere's what we get when we plug in $6$:\n\n$\\begin{align}f(6)&=\\blueD{-27e^{6}} \\maroonD{+ C}\n\\end{align}$ \n\nWe are given that this must equal $36-27e^6$:\n\n$36-27e^6 = \\blueD{-27e^{6}} \\maroonD{+ C}$\n\nSolving the equation gives us $\\maroonD{C=36}$. ", "##Finding $f(0)$\n\nNow, we have that $f(x)=\\blueD{-27e^x} \\maroonD{+ 36}$. \n\nLet's find $f(0)$ by plugging in $0$:\n\n$\\begin{align}f(0)&=-27e^0 + 36\\\\\\\\\n&=9\n\\end{align}$ ", "##The answer\n\n$f(0) = 9$"], "widget_types": ["numeric-input"], "answer_data": {"numeric-input 2": {"type": "numeric-input", "answers": [{"maxError": null, "message": "", "simplify": "required", "status": "correct", "strict": false, "value": 9}]}}}, {"item_id": "27a7279faad858f48924e22638820476", "question_content": "**$f\\,^{\\prime}(x)=5e^x$ and $f(7)=40+5e^7$.** \n\n$f(0) = $ [[☃ numeric-input 2]]", "hints": ["##Finding $f(x)$\n\nWe have $f'(x)=5e^x$ and we want to find $f(x)$:\n\n$\\begin{align}f(x) &= \\displaystyle \\int f'(x)\\,dx\n\\\\\\\\\n& = \\displaystyle \\int (5e^x)\\,dx\n\\\\\\\\\n& =  \\blueD{5e^x} \\maroonD{+ C}\n\\end{align}$", "##Finding $\\maroonD C$\n\n**Goal:** We need to find $\\maroonD C$ such that $f(7)=40+5e^7$. \n\nHere's what we get when we plug in $7$:\n\n$\\begin{align}f(7)&=\\blueD{5e^{7}} \\maroonD{+ C}\n\\end{align}$ \n\nWe are given that this must equal $40+5e^7$:\n\n$40+5e^7 = \\blueD{5e^{7}} \\maroonD{+ C}$\n\nSolving the equation gives us $\\maroonD{C=40}$. ", "##Finding $f(0)$\n\nNow, we have that $f(x)=\\blueD{5e^x} \\maroonD{+ 40}$. \n\nLet's find $f(0)$ by plugging in $0$:\n\n$\\begin{align}f(0)&=5e^0 + 40\\\\\\\\\n&=45\n\\end{align}$ ", "##The answer\n\n$f(0) = 45$"], "widget_types": ["numeric-input"], "answer_data": {"numeric-input 2": {"type": "numeric-input", "answers": [{"maxError": null, "message": "", "simplify": "required", "status": "correct", "strict": false, "value": 45}]}}}, {"item_id": "0a625f8f143e56099042e067e362be5f", "question_content": "**$f\\,^{\\prime}(x)=9e^x$ and $f(8)=-8+9e^8$.** \n\n$f(0) = $ [[☃ numeric-input 2]]", "hints": ["##Finding $f(x)$\n\nWe have $f'(x)=9e^x$ and we want to find $f(x)$:\n\n$\\begin{align}f(x) &= \\displaystyle \\int f'(x)\\,dx\n\\\\\\\\\n& = \\displaystyle \\int (9e^x)\\,dx\n\\\\\\\\\n& =  \\blueD{9e^x} \\maroonD{+ C}\n\\end{align}$", "##Finding $\\maroonD C$\n\n**Goal:** We need to find $\\maroonD C$ such that $f(8)=-8+9e^8$. \n\nHere's what we get when we plug in $8$:\n\n$\\begin{align}f(8)&=\\blueD{9e^{8}} \\maroonD{+ C}\n\\end{align}$ \n\nWe are given that this must equal $-8+9e^8$:\n\n$-8+9e^8 = \\blueD{9e^{8}} \\maroonD{+ C}$\n\nSolving the equation gives us $\\maroonD{C=-8}$. ", "##Finding $f(0)$\n\nNow, we have that $f(x)=\\blueD{9e^x} \\maroonD{-8}$. \n\nLet's find $f(0)$ by plugging in $0$:\n\n$\\begin{align}f(0)&=9e^0 - 8\\\\\\\\\n&=1\n\\end{align}$ ", "##The answer\n\n$f(0) = 1$"], "widget_types": ["numeric-input"], "answer_data": {"numeric-input 2": {"type": "numeric-input", "answers": [{"maxError": null, "message": "", "simplify": "required", "status": "correct", "strict": false, "value": 1}]}}}, {"item_id": "a4c81683ae0059708509b731e4c02790", "question_content": "**$f\\,^{\\prime}(x)=-\\dfrac{4}{x^2}$ and $f(2)=4$.** \n\n$f(1) = $ [[☃ numeric-input 2]]", "hints": ["##Finding $f(x)$\n\nWe have $f'(x)=-\\dfrac{4}{x^2}$ and we want to find $f(x)$:\n\n$\\begin{align}f(x) &= \\displaystyle \\int f'(x)\\,dx\n\\\\\\\\\n& = \\displaystyle \\int (-\\dfrac{4}{x^2})\\,dx\n\\\\\\\\\n& =  \\blueD{4x^{-1}} \\maroonD{+ C}\n\\end{align}$", "##Finding $\\maroonD C$\n\n**Goal:** We need to find $\\maroonD C$ such that $f(2)=4$. \n\nHere's what we get when we plug in $2$:\n\n$\\begin{align}f(2)&=\\blueD{4(2)^{-1}} \\maroonD{+ C}\\\\\\\\\n&=\\blueD{2} \\maroonD{+ C} \n\\end{align}$ \n\nWe are given that this must equal $4$:\n\n$4 = \\blueD{2} \\maroonD{+ C}$\n\nSolving the equation gives us $\\maroonD{C=2}$. ", "##Finding $f(2)$\n\nNow, we have that $f(x)= \\blueD{4x^{-1}} \\maroonD{+2}$. \n\nLet's find $f(1)$ by plugging in $1$:\n\n$\\begin{align}f(1)&=4(1)^{-1}+2\\\\\\\\\n&=6\n\\end{align}$ ", "##The answer\n\n$f(1) = 6$"], "widget_types": ["numeric-input"], "answer_data": {"numeric-input 2": {"type": "numeric-input", "answers": [{"maxError": null, "message": "", "simplify": "required", "status": "correct", "strict": false, "value": 6}]}}}, {"item_id": "01831f96bd5659a98fc0b7fba285299d", "question_content": "**$f\\,^{\\prime}(x)=-\\dfrac{6}{x^4}$ and $f(1)=-4$.** \n\n$f(-1) = $ [[☃ numeric-input 2]]", "hints": ["##Finding $f(x)$\n\nWe have $f'(x)=-\\dfrac{6}{x^4}$ and we want to find $f(x)$:\n\n$\\begin{align}f(x) &= \\displaystyle \\int f'(x)\\,dx\n\\\\\\\\\n& = \\displaystyle \\int (-\\dfrac{6}{x^4})\\,dx\n\\\\\\\\\n& =  \\blueD{2x^{-3}} \\maroonD{+ C}\n\\end{align}$", "##Finding $\\maroonD C$\n\n**Goal:** We need to find $\\maroonD C$ such that $f(1)=-4$. \n\nHere's what we get when we plug in $1$:\n\n$\\begin{align}f(1)&=\\blueD{2(1)^{-3}} \\maroonD{+ C}\\\\\\\\\n&=\\blueD{2} \\maroonD{+ C} \n\\end{align}$ \n\nWe are given that this must equal $-4$:\n\n$-4 = \\blueD{2} \\maroonD{+ C}$\n\nSolving the equation gives us $\\maroonD{C=-6}$. ", "##Finding $f(-1)$\n\nNow, we have that $f(x)= \\blueD{2x^{-3}} \\maroonD{-6}$. \n\nLet's find $f(-1)$ by plugging in $-1$:\n\n$\\begin{align}f(-1)&=2(-1)^{-3}-6\\\\\\\\\n&=-8\n\\end{align}$ ", "##The answer\n\n$f(-1) = -8$"], "widget_types": ["numeric-input"], "answer_data": {"numeric-input 2": {"type": "numeric-input", "answers": [{"maxError": null, "message": "", "simplify": "required", "status": "correct", "strict": false, "value": -8}]}}}, {"item_id": "8a175ab95647549188d011aeed2225f1", "question_content": "**$f\\,^{\\prime}(x)=\\dfrac{24}{x^3}$ and $f(2)=12$.** \n\n$f(-1) = $ [[☃ numeric-input 2]]", "hints": ["##Finding $f(x)$\n\nWe have $f'(x)=\\dfrac{24}{x^3}$ and we want to find $f(x)$:\n\n$\\begin{align}f(x) &= \\displaystyle \\int f'(x)\\,dx\n\\\\\\\\\n& = \\displaystyle \\int \\dfrac{24}{x^3}\\,dx\n\\\\\\\\\n& =  \\blueD{-12x^{-2}} \\maroonD{+ C}\n\\end{align}$", "##Finding $\\maroonD C$\n\n**Goal:** We need to find $\\maroonD C$ such that $f(2)=12$. \n\nHere's what we get when we plug in $2$:\n\n$\\begin{align}f(2)&=\\blueD{-12(2)^{-2}} \\maroonD{+ C}\\\\\\\\\n&=\\blueD{-3} \\maroonD{+ C} \n\\end{align}$ \n\nWe are given that this must equal $12$:\n\n$12 = \\blueD{-3} \\maroonD{+ C}$\n\nSolving the equation gives us $\\maroonD{C=15}$. ", "##Finding $f(-1)$\n\nNow, we have that $f(x)= \\blueD{-12x^{-2}} \\maroonD{+15}$. \n\nLet's find $f(-1)$ by plugging in $-1$:\n\n$\\begin{align}f(-1)&=-12(-1)^{-2}+15\\\\\\\\\n&=3\n\\end{align}$ ", "##The answer\n\n$f(-1) = 3$"], "widget_types": ["numeric-input"], "answer_data": {"numeric-input 2": {"type": "numeric-input", "answers": [{"maxError": null, "message": "", "simplify": "required", "status": "correct", "strict": false, "value": 3}]}}}, {"item_id": "d9f97c3b8b4155b9aa0eff9a3095ab13", "question_content": "**$f\\,^{\\prime}(x)=\\dfrac{100}{x^3}$ and $f(5)=-14$.** \n\n$f(1) = $ [[☃ numeric-input 2]]", "hints": ["##Finding $f(x)$\n\nWe have $f'(x)=\\dfrac{100}{x^3}$ and we want to find $f(x)$:\n\n$\\begin{align}f(x)& = \\displaystyle \\int f'(x)\\,dx\n\\\\\\\\\n& = \\displaystyle \\int \\dfrac{100}{x^3}\\,dx\n\\\\\\\\\n& =  \\blueD{-50x^{-2}} \\maroonD{+ C}\n\\end{align}$", "##Finding $\\maroonD C$\n\n**Goal:** We need to find $\\maroonD C$ such that $f(5)=-14$. \n\nHere's what we get when we plug in $5$:\n\n$\\begin{align}f(5)&=\\blueD{-50(5)^{-2}} \\maroonD{+ C}\\\\\\\\\n&=\\blueD{-2} \\maroonD{+ C} \n\\end{align}$ \n\nWe are given that this must equal $-14$:\n\n$-14 = \\blueD{-2} \\maroonD{+ C}$\n\nSolving the equation gives us $\\maroonD{C=-12}$. ", "##Finding $f(1)$\n\nNow, we have that $f(x)= \\blueD{50x^{-2}} \\maroonD{-12}$. \n\nLet's find $f(1)$ by plugging in $1$:\n\n$\\begin{align}f(1)&=-50(1)^{-2}-12\\\\\\\\\n&=-62\n\\end{align}$ ", "##The answer\n\n$f(1) =- 62$"], "widget_types": ["numeric-input"], "answer_data": {"numeric-input 2": {"type": "numeric-input", "answers": [{"maxError": null, "message": "", "simplify": "required", "status": "correct", "strict": false, "value": -62}]}}}, {"item_id": "505d3b0700b75b9489de9a06661ec477", "question_content": "**$f\\,^{\\prime}(x)=\\dfrac{16}{x^2}$ and $f(-2)=0$.** \n\n$f(4) = $ [[☃ numeric-input 2]]", "hints": ["##Finding $f(x)$\n\nWe have $f'(x)=\\dfrac{16}{x^2}$ and we want to find $f(x)$:\n\n$\\begin{align}f(x) &= \\displaystyle \\int f'(x)\\,dx\n\\\\\\\\\n& = \\displaystyle \\int \\dfrac{16}{x^2}\\,dx\n\\\\\\\\\n& =  \\blueD{-16x^{-1}} \\maroonD{+ C}\n\\end{align}$", "##Finding $\\maroonD C$\n\n**Goal:** We need to find $\\maroonD C$ such that $f(-2)=0$. \n\nHere's what we get when we plug in $-2$:\n\n$\\begin{align}f(-2)&=\\blueD{-16(-2)^{-1}} \\maroonD{+ C}\\\\\\\\\n&=\\blueD{8} \\maroonD{+ C} \n\\end{align}$ \n\nWe are given that this must equal $0$:\n\n$0 = \\blueD{8} \\maroonD{+ C}$\n\nSolving the equation gives us $\\maroonD{C=-8}$. ", "##Finding $f(4)$\n\nNow, we have that $f(x)= \\blueD{-16x^{-1}} \\maroonD{-8}$. \n\nLet's find $f(4)$ by plugging in $4$:\n\n$\\begin{align}f(4)&=-16(4)^{-1}-8\\\\\\\\\n&=-12\n\\end{align}$ ", "##The answer\n\n$f(4) = -12$"], "widget_types": ["numeric-input"], "answer_data": {"numeric-input 2": {"type": "numeric-input", "answers": [{"maxError": null, "message": "", "simplify": "required", "status": "correct", "strict": false, "value": -12}]}}}, {"item_id": "6ebbe6dc78d65021ab28b95b0ebcdba0", "question_content": "**$f\\,^{\\prime}(x)=-\\dfrac{50}{x^3}$ and $f(1)=20$.** \n\n$f(5) = $ [[☃ numeric-input 2]]", "hints": ["##Finding $f(x)$\n\nWe have $f'(x)=-\\dfrac{50}{x^3}$ and we want to find $f(x)$:\n\n$\\begin{align}f(x)& = \\displaystyle \\int f'(x)\\,dx\n\\\\\\\\\n& = \\displaystyle \\int (-\\dfrac{50}{x^3})\\,dx\n\\\\\\\\\n& =  \\blueD{25x^{-2}} \\maroonD{+ C}\n\\end{align}$", "##Finding $\\maroonD C$\n\n**Goal:** We need to find $\\maroonD C$ such that $f(1)=20$. \n\nHere's what we get when we plug in $1$:\n\n$\\begin{align}f(1)&=\\blueD{25(1)^{-2}} \\maroonD{+ C}\\\\\\\\\n&=\\blueD{25} \\maroonD{+ C} \n\\end{align}$ \n\nWe are given that this must equal $20$:\n\n$20 = \\blueD{25} \\maroonD{+ C}$\n\nSolving the equation gives us $\\maroonD{C=-5}$. ", "##Finding $f(5)$\n\nNow, we have that $f(x)= \\blueD{25x^{-2}} \\maroonD{-5}$. \n\nLet's find $f(5)$ by plugging in $5$:\n\n$\\begin{align}f(5)&=25(5)^{-2}-5\\\\\\\\\n&=-4\n\\end{align}$ ", "##The answer\n\n$f(5) = -4$"], "widget_types": ["numeric-input"], "answer_data": {"numeric-input 2": {"type": "numeric-input", "answers": [{"maxError": null, "message": "", "simplify": "required", "status": "correct", "strict": false, "value": -4}]}}}, {"item_id": "80bfe2e80c445ae1b44c0374e34b8798", "question_content": "**$f\\,^{\\prime}(x)=-\\dfrac{320}{x^6}$ and $f(1)=30$.** \n\n$f(-2) = $ [[☃ numeric-input 2]]", "hints": ["##Finding $f(x)$\n\nWe have $f'(x)=-\\dfrac{320}{x^6}$ and we want to find $f(x)$:\n\n$\\begin{align}f(x)& = \\displaystyle \\int f'(x)\\,dx\n\\\\\\\\\n& = \\displaystyle \\int (-\\dfrac{320}{x^6})\\,dx\n\\\\\\\\\n& =  \\blueD{64x^{-5}} \\maroonD{+ C}\n\\end{align}$", "##Finding $\\maroonD C$\n\n**Goal:** We need to find $\\maroonD C$ such that $f(1)=30$. \n\nHere's what we get when we plug in $1$:\n\n$\\begin{align}f(1)&=\\blueD{64(1)^{-5}} \\maroonD{+ C}\\\\\\\\\n&=\\blueD{64} \\maroonD{+ C} \n\\end{align}$ \n\nWe are given that this must equal $30$:\n\n$30 = \\blueD{64} \\maroonD{+ C}$\n\nSolving the equation gives us $\\maroonD{C=-34}$. ", "##Finding $f(-2)$\n\nNow, we have that $f(x)= \\blueD{64x^{-5}} \\maroonD{-34}$. \n\nLet's find $f(-2)$ by plugging in $-2$:\n\n$\\begin{align}f(-2)&=64(-2)^{-5}-34\\\\\\\\\n&=-36\n\\end{align}$ ", "##The answer\n\n$f(-2) = -36$"], "widget_types": ["numeric-input"], "answer_data": {"numeric-input 2": {"type": "numeric-input", "answers": [{"maxError": null, "message": "", "simplify": "required", "status": "correct", "strict": false, "value": -36}]}}}, {"item_id": "35709e66ef4a580e8c3469d77cef32d8", "question_content": "**$f\\,^{\\prime}(x)=\\dfrac{81}{x^4}$ and $f(-1)=18$.** \n\n$f(3) = $ [[☃ numeric-input 2]]", "hints": ["##Finding $f(x)$\n\nWe have $f'(x)=\\dfrac{81}{x^4}$ and we want to find $f(x)$:\n\n$\\begin{align}f(x) &= \\displaystyle \\int f'(x)\\,dx\n\\\\\\\\\n& = \\displaystyle \\int \\dfrac{81}{x^4}\\,dx\n\\\\\\\\\n& =  \\blueD{-27x^{-3}} \\maroonD{+ C}\n\\end{align}$", "##Finding $\\maroonD C$\n\n**Goal:** We need to find $\\maroonD C$ such that $f(-1)=18$. \n\nHere's what we get when we plug in $-1$:\n\n$\\begin{align}f(-1)&=\\blueD{-27(-1)^{-3}} \\maroonD{+ C}\\\\\\\\\n&=\\blueD{27} \\maroonD{+ C} \n\\end{align}$ \n\nWe are given that this must equal $18$:\n\n$18 = \\blueD{27} \\maroonD{+ C}$\n\nSolving the equation gives us $\\maroonD{C=-9}$. ", "##Finding $f(3)$\n\nNow, we have that $f(x)= \\blueD{-27x^{-3}} \\maroonD{-9}$. \n\nLet's find $f(3)$ by plugging in $3$:\n\n$\\begin{align}f(3)&=-27(3)^{-3}-9\\\\\\\\\n&=-10\n\\end{align}$ ", "##The answer\n\n$f(3) = -10$"], "widget_types": ["numeric-input"], "answer_data": {"numeric-input 2": {"type": "numeric-input", "answers": [{"maxError": null, "message": "", "simplify": "required", "status": "correct", "strict": false, "value": -10}]}}}], "mastery_model": {"type": "m_of_n", "m": 3, "n": 4}, "randomize": true}