{"node_id": "4a22ff9b89365d96bbb8db3de7d637e9", "title": "Write decimals as fractions", "description": "Practice writing decimals as fractions. These problems use decimals with tenths and hundredths.", "topic_path": ["Khan Academy (English - US curriculum)", "Math by grade", "Get ready for 8th grade", "Get ready for numbers and operations", "Converting fractions to decimals", "Write decimals as fractions"], "assessment_items": [{"item_id": "60a53fc6cf4f5fdc8bce36fdf22ad311", "question_content": "**Express $0.1$ as a fraction.**\n\n[[☃ numeric-input 1]]", "hints": ["Let's look at $0.1$ on a place value table.\n\nOnes |. | Tenths | Hundredths\n:-: | :-: | :-: | :-:  \n$0$ | .| $\\blueD1$ | ", "The number $\\blueD1$ is in the tenths place, so we have one tenth.", "$0.1$ can be written as $\\dfrac{\\blueD1}{10}$.\n\n[[☃ explanation 1]]"], "widget_types": ["numeric-input"], "answer_data": {"numeric-input 1": {"type": "numeric-input", "answers": [{"answerForms": ["proper"], "maxError": 0, "message": "", "simplify": "optional", "status": "correct", "strict": true, "value": 0.1}]}}}, {"item_id": "3aab650ffce258c7880fbda701c756a2", "question_content": "**Express $0.2$ as a fraction.**\n\n[[☃ numeric-input 1]]", "hints": ["Let's look at $0.2$ on a place value table.\n\nOnes |. | Tenths | Hundredths\n:-: | :-: | :-: | :-:  \n$0$ | .| $\\blueD2$ | \n\n", "The number $\\blueD2$ is in the tenths place, so we have two tenths.", "$0.2$ can be written as $\\dfrac{\\blueD2}{10}$ .\n\n[[☃ explanation 1]]"], "widget_types": ["numeric-input"], "answer_data": {"numeric-input 1": {"type": "numeric-input", "answers": [{"answerForms": ["proper"], "maxError": 0, "message": "", "simplify": "optional", "status": "correct", "strict": true, "value": 0.2}]}}}, {"item_id": "59f679c1834a53bc938cf3d1a961b958", "question_content": "**Express $0.3$ as a fraction.**\n\n[[☃ numeric-input 1]]", "hints": ["Let's look at $0.3$ on a place value table.\n\nOnes |. | Tenths | Hundredths\n:-: | :-: | :-: | :-:  \n$0$ | .| $\\blueD3$ | \n", "The number $\\blueD3$ is in the tenths place, so we have three tenths.", "$0.3$ can be written as $\\dfrac{\\blueD3}{10}$.\n\n[[☃ explanation 1]]"], "widget_types": ["numeric-input"], "answer_data": {"numeric-input 1": {"type": "numeric-input", "answers": [{"answerForms": ["proper"], "maxError": 0, "message": "", "simplify": "optional", "status": "correct", "strict": true, "value": 0.3}]}}}, {"item_id": "bcb9252ab8c65625b7156f68c7e37f0c", "question_content": "**Express $0.4$ as a fraction.**\n\n[[☃ numeric-input 1]]", "hints": ["Let's look at $0.4$ on a place value table.\n\nOnes |. | Tenths | Hundredths\n:-: | :-: | :-: | :-:  \n$0$ | .| $\\blueD4$ | ", "The number $\\blueD4$ is in the tenths place, so we have four tenths.", "$0.4$ can be written as $\\dfrac{\\blueD4}{10}$.\n\n[[☃ explanation 1]]"], "widget_types": ["numeric-input"], "answer_data": {"numeric-input 1": {"type": "numeric-input", "answers": [{"answerForms": ["proper"], "maxError": 0, "message": "", "simplify": "optional", "status": "correct", "strict": true, "value": 0.4}]}}}, {"item_id": "f73f2bd7d5935f5abf55f8d157c51f23", "question_content": "**Express $0.5$ as a fraction.**\n\n[[☃ numeric-input 1]]", "hints": ["Let's look at $0.5$ on a place value table.\n\nOnes |. | Tenths | Hundredths\n:-: | :-: | :-: | :-:  \n$0$ | .| $\\blueD5$ | ", "The number $\\blueD5$ is in the tenths place, so we have five tenths.", "$0.5$ can be written as $\\dfrac{\\blueD5}{10}$.\n\n[[☃ explanation 1]]"], "widget_types": ["numeric-input"], "answer_data": {"numeric-input 1": {"type": "numeric-input", "answers": [{"answerForms": ["proper"], "maxError": 0, "message": "", "simplify": "optional", "status": "correct", "strict": true, "value": 0.5}]}}}, {"item_id": "a27b5381710a5bf4abc9fa5e7bedba2c", "question_content": "**Express $0.6$ as a fraction.**\n\n[[☃ numeric-input 1]]", "hints": ["Let's look at $0.6$ on a place value table.\n\nOnes |. | Tenths | Hundredths\n:-: | :-: | :-: | :-:  \n$0$ | .| $\\blueD6$ | \n", "The number $\\blueD6$ is in the tenths place, so we have six tenths.", "$0.6$ can be written as $\\dfrac{\\blueD6}{10}$.\n\n[[☃ explanation 1]]"], "widget_types": ["numeric-input"], "answer_data": {"numeric-input 1": {"type": "numeric-input", "answers": [{"answerForms": ["proper"], "maxError": 0, "message": "", "simplify": "optional", "status": "correct", "strict": true, "value": 0.6}]}}}, {"item_id": "b4a8bb6c44cb5fc5b597bd8ce3f633a8", "question_content": "**Express $0.7$ as a fraction.**\n\n[[☃ numeric-input 1]]", "hints": ["Let's look at $0.7$ on a place value table.\n\nOnes |. | Tenths | Hundredths\n:-: | :-: | :-: | :-:  \n$0$ | .| $\\blueD7$ | ", "The number $\\blueD7$ is in the tenths place, so we have seven tenths.", "$0.7$ can be written as $\\dfrac{\\blueD7}{10}$.\n\n[[☃ explanation 1]]"], "widget_types": ["numeric-input"], "answer_data": {"numeric-input 1": {"type": "numeric-input", "answers": [{"answerForms": ["proper"], "maxError": 0, "message": "", "simplify": "optional", "status": "correct", "strict": true, "value": 0.7}]}}}, {"item_id": "af0dc68c799455088c41c92abf941591", "question_content": "**Express $0.8$ as a fraction.**\n\n[[☃ numeric-input 1]]", "hints": ["Let's look at $0.8$ on a place value table.\n\nOnes |. | Tenths | Hundredths\n:-: | :-: | :-: | :-:  \n$0$ | .| $\\blueD8$ | ", "The number $\\blueD8$ is in the tenths place, so we have eight tenths.", "$0.8$ can be written as $\\dfrac{\\blueD8}{10}$.\n\n[[☃ explanation 1]]"], "widget_types": ["numeric-input"], "answer_data": {"numeric-input 1": {"type": "numeric-input", "answers": [{"answerForms": ["proper"], "maxError": 0, "message": "", "simplify": "optional", "status": "correct", "strict": true, "value": 0.8}]}}}, {"item_id": "5640fa1138185606a49556d91f784508", "question_content": "**Express $0.9$ as a fraction.**\n\n[[☃ numeric-input 1]]", "hints": ["Let's look at $0.9$ on a place value table.\n\nOnes |. | Tenths | Hundredths\n:-: | :-: | :-: | :-:  \n$0$ | .| $\\blueD9$ | ", "The number $\\blueD9$ is in the tenths place, so we have nine tenths.", "$0.9$ can be written as $\\dfrac{\\blueD9}{10}$.\n\n[[☃ explanation 1]]"], "widget_types": ["numeric-input"], "answer_data": {"numeric-input 1": {"type": "numeric-input", "answers": [{"answerForms": ["proper"], "maxError": 0, "message": "", "simplify": "optional", "status": "correct", "strict": true, "value": 0.9}]}}}, {"item_id": "96da9a3a0778587ba287baf405bceac0", "question_content": "**Express $0.01$ as a fraction.**\n\n[[☃ numeric-input 1]]", "hints": ["Let's look at $0.01$ on a place value table.\n\nOnes |. | Tenths | Hundredths\n:-: | :-: | :-: | :-:  \n$0$ | .| $\\blueD0$ | $\\purpleC1$\n", "We have a $\\blueD0$ in the tenths place.\n\nWe can write zero tenths as $\\dfrac{\\blueD0}{10}$.", "We have a $\\purpleC1$ in the hundredths place.\n\nWe can write one hundredth as $\\dfrac{\\purpleC1}{100}$.", "Add the two parts together.\n\n $\\dfrac{\\blueD0}{10} + \\dfrac{\\purpleC1}{100}$", "$\\begin{align}\n=& {\\blueD0} + \\dfrac{\\purpleC1}{100}\\\\\\\\\n=& \\dfrac{\\purpleC1}{100}\n\\end{align}$\n\n[[☃ explanation 1]]"], "widget_types": ["numeric-input"], "answer_data": {"numeric-input 1": {"type": "numeric-input", "answers": [{"answerForms": ["proper", "improper"], "maxError": 0, "message": "", "simplify": "optional", "status": "correct", "strict": true, "value": 0.01}]}}}, {"item_id": "b7b703aea52e506c80aa0d99bf774983", "question_content": "**Express $0.02$ as a fraction.**\n\n[[☃ numeric-input 1]]", "hints": ["Let's look at $0.02$ on a place value table.\n\nOnes |. | Tenths | Hundredths\n:-: | :-: | :-: | :-:  \n$0$ | .| $\\blueD0$ | $\\purpleC2$", "We have a $\\blueD0$ in the tenths place.\n\nWe can write zero tenths as $\\dfrac{\\blueD0}{10}$.", "We have a $\\purpleC2$ in the hundredths place.\n\nWe can write two hundredths as $\\dfrac{\\purpleC2}{100}$.", "Add the two parts together.\n\n $\\dfrac{\\blueD0}{10} + \\dfrac{\\purpleC2}{100}$", "$\\begin{align}\n=& {\\blueD0} + \\dfrac{\\purpleC2}{100}\\\\\\\\\n=& \\dfrac{\\purpleC2}{100}\n\\end{align}$\n\n[[☃ explanation 1]]"], "widget_types": ["numeric-input"], "answer_data": {"numeric-input 1": {"type": "numeric-input", "answers": [{"answerForms": ["proper", "improper"], "maxError": 0, "message": "", "simplify": "optional", "status": "correct", "strict": true, "value": 0.02}]}}}, {"item_id": "622e19e78df551f8bcdf4b87af424049", "question_content": "**Express $0.03$ as a fraction.**\n\n[[☃ numeric-input 1]]", "hints": ["Let's look at $0.03$ on a place value table.\n\nOnes |. | Tenths | Hundredths\n:-: | :-: | :-: | :-:  \n$0$ | .| $\\blueD0$ | $\\purpleC3$", "We have a $\\blueD0$ in the tenths place.\n\nWe can write zero tenths as $\\dfrac{\\blueD0}{10}$.", "We have a $\\purpleC3$ in the hundredths place.\n\nWe can write three hundredths as $\\dfrac{\\purpleC3}{100}$.", "Add the two parts together.\n\n $\\dfrac{\\blueD0}{10} + \\dfrac{\\purpleC3}{100}$", "$\\begin{align}\n=& {\\blueD0} + \\dfrac{\\purpleC3}{100}\\\\\\\\\n=& \\dfrac{\\purpleC3}{100}\n\\end{align}$\n\n[[☃ explanation 1]]"], "widget_types": ["numeric-input"], "answer_data": {"numeric-input 1": {"type": "numeric-input", "answers": [{"answerForms": ["proper", "improper"], "maxError": 0, "message": "", "simplify": "optional", "status": "correct", "strict": true, "value": 0.03}]}}}, {"item_id": "888c313d93715f03a15846b212e5d150", "question_content": "**Express $0.04$ as a fraction.**\n\n[[☃ numeric-input 1]]", "hints": ["Let's look at $0.04$ on a place value table.\n\nOnes |. | Tenths | Hundredths\n:-: | :-: | :-: | :-:  \n$0$ | .| $\\blueD0$ | $\\purpleC4$", "We have a $\\blueD0$ in the tenths place.\n\nWe can write zero tenths as $\\dfrac{\\blueD0}{10}$.", "We have a $\\purpleC4$ in the hundredths place.\n\nWe can write four hundredths as $\\dfrac{\\purpleC4}{100}$.", "Add the two parts together.\n\n $\\dfrac{\\blueD0}{10} + \\dfrac{\\purpleC4}{100}$", "$\\begin{align}\n=& {\\blueD0} + \\dfrac{\\purpleC4}{100}\\\\\\\\\n=& \\dfrac{\\purpleC4}{100}\n\\end{align}$\n\n[[☃ explanation 1]]"], "widget_types": ["numeric-input"], "answer_data": {"numeric-input 1": {"type": "numeric-input", "answers": [{"answerForms": ["proper", "improper"], "maxError": 0, "message": "", "simplify": "optional", "status": "correct", "strict": true, "value": 0.04}]}}}, {"item_id": "c3c6d55a88e95958a10d58a5b82012ce", "question_content": "**Express $0.05$ as a fraction.**\n\n[[☃ numeric-input 1]]", "hints": ["Let's look at $0.05$ on a place value table.\n\nOnes |. | Tenths | Hundredths\n:-: | :-: | :-: | :-:  \n$0$ | .| $\\blueD0$ | $\\purpleC5$", "We have a $\\blueD0$ in the tenths place.\n\nWe can write zero tenths as $\\dfrac{\\blueD0}{10}$.", "We have a $\\purpleC5$ in the hundredths place.\n\nWe can write five hundredths as $\\dfrac{\\purpleC5}{100}$.", "Add the two parts together.\n\n $\\dfrac{\\blueD0}{10} + \\dfrac{\\purpleC5}{100}$", "$\\begin{align}\n=& {\\blueD0} + \\dfrac{\\purpleC5}{100}\\\\\\\\\n=& \\dfrac{\\purpleC5}{100}\n\\end{align}$\n\n[[☃ explanation 1]]"], "widget_types": ["numeric-input"], "answer_data": {"numeric-input 1": {"type": "numeric-input", "answers": [{"answerForms": ["proper", "improper"], "maxError": 0, "message": "", "simplify": "optional", "status": "correct", "strict": true, "value": 0.05}]}}}, {"item_id": "3513ac07853d5003826c7f089a434643", "question_content": "**Express $0.06$ as a fraction.**\n\n[[☃ numeric-input 1]]", "hints": ["Let's look at $0.06$ on a place value table.\n\nOnes |. | Tenths | Hundredths\n:-: | :-: | :-: | :-:  \n$0$ | .| $\\blueD0$ | $\\purpleC6$", "We have a $\\blueD0$ in the tenths place.\n\nWe can write zero tenths as $\\dfrac{\\blueD0}{10}$.", "We have a $\\purpleC6$ in the hundredths place.\n\nWe can write six hundredths as $\\dfrac{\\purpleC6}{100}$.", "Add the two parts together.\n\n $\\dfrac{\\blueD0}{10} + \\dfrac{\\purpleC6}{100}$", "$\\begin{align}\n=& {\\blueD0} + \\dfrac{\\purpleC6}{100}\\\\\\\\\n=& \\dfrac{\\purpleC6}{100}\n\\end{align}$\n\n[[☃ explanation 1]]"], "widget_types": ["numeric-input"], "answer_data": {"numeric-input 1": {"type": "numeric-input", "answers": [{"answerForms": ["proper", "improper"], "maxError": 0, "message": "", "simplify": "optional", "status": "correct", "strict": true, "value": 0.06}]}}}, {"item_id": "c75d3692a9775ebab83f18bd3c9c24b7", "question_content": "**Express $0.07$ as a fraction.**\n\n[[☃ numeric-input 1]]", "hints": ["Let's look at $0.07$ on a place value table.\n\nOnes |. | Tenths | Hundredths\n:-: | :-: | :-: | :-:  \n$0$ | .| $\\blueD0$ | $\\purpleC7$", "We have a $\\blueD0$ in the tenths place.\n\nWe can write zero tenths as $\\dfrac{\\blueD0}{10}$.", "We have a $\\purpleC7$ in the hundredths place.\n\nWe can write seven hundredths as $\\dfrac{\\purpleC7}{100}$.", "Add the two parts together.\n\n $\\dfrac{\\blueD0}{10} + \\dfrac{\\purpleC7}{100}$", "$\\begin{align}\n=& {\\blueD0} + \\dfrac{\\purpleC7}{100}\\\\\\\\\n=& \\dfrac{\\purpleC7}{100}\n\\end{align}$\n\n[[☃ explanation 1]]"], "widget_types": ["numeric-input"], "answer_data": {"numeric-input 1": {"type": "numeric-input", "answers": [{"answerForms": ["proper", "improper"], "maxError": 0, "message": "", "simplify": "optional", "status": "correct", "strict": true, "value": 0.07}]}}}, {"item_id": "eeb4dd8b029652958a93236c2b852bbe", "question_content": "**Express $0.08$ as a fraction.**\n\n[[☃ numeric-input 1]]", "hints": ["Let's look at $0.08$ on a place value table.\n\nOnes |. | Tenths | Hundredths\n:-: | :-: | :-: | :-:  \n$0$ | .| $\\blueD0$ | $\\purpleC8$", "We have a $\\blueD0$ in the tenths place.\n\nWe can write zero tenths as $\\dfrac{\\blueD0}{10}$.", "We have a $\\purpleC8$ in the hundredths place.\n\nWe can write eight hundredths as $\\dfrac{\\purpleC8}{100}$.", "Add the two parts together.\n\n $\\dfrac{\\blueD0}{10} + \\dfrac{\\purpleC8}{100}$", "$\\begin{align}\n=& {\\blueD0} + \\dfrac{\\purpleC8}{100}\\\\\\\\\n=& \\dfrac{\\purpleC8}{100}\n\\end{align}$\n\n[[☃ explanation 1]]"], "widget_types": ["numeric-input"], "answer_data": {"numeric-input 1": {"type": "numeric-input", "answers": [{"answerForms": ["proper", "improper"], "maxError": 0, "message": "", "simplify": "optional", "status": "correct", "strict": true, "value": 0.08}]}}}, {"item_id": "cdd9e85cbb0f5d7193140532c1548475", "question_content": "**Express $0.09$ as a fraction.**\n\n[[☃ numeric-input 1]]", "hints": ["Let's look at $0.09$ on a place value table.\n\nOnes |. | Tenths | Hundredths\n:-: | :-: | :-: | :-:  \n$0$ | .| $\\blueD0$ | $\\purpleC9$", "We have a $\\blueD0$ in the tenths place.\n\nWe can write zero tenths as $\\dfrac{\\blueD0}{10}$.", "We have a $\\purpleC9$ in the hundredths place.\n\nWe can write nine hundredths as $\\dfrac{\\purpleC9}{100}$.", "Add the two parts together.\n\n $\\dfrac{\\blueD0}{10} + \\dfrac{\\purpleC9}{100}$", "$\\begin{align}\n=& {\\blueD0} + \\dfrac{\\purpleC9}{100}\\\\\\\\\n=& \\dfrac{\\purpleC9}{100}\n\\end{align}$\n\n[[☃ explanation 1]]"], "widget_types": ["numeric-input"], "answer_data": {"numeric-input 1": {"type": "numeric-input", "answers": [{"answerForms": ["proper", "improper"], "maxError": 0, "message": "", "simplify": "optional", "status": "correct", "strict": true, "value": 0.09}]}}}, {"item_id": "d8ce06ffebc258449b8aa6bcfdaadc70", "question_content": "**Express $0.11$ as a fraction.**\n\n[[☃ numeric-input 1]]", "hints": ["Let's look at $0.11$ on a place value table.\n\nOnes |. | Tenths | Hundredths\n:-: | :-: | :-: | :-:  \n$0$ | .| $\\blueD1$ | $\\purpleC1$", "The number $\\blueD1$ is in the tenths place, so we have one tenth.\n\nOne tenth can be written as $\\dfrac{\\blueD1}{10}$.", "The number $\\purpleC1$ is in the hundredths place, so we have one hundredth.\n\nOne hundredth can be written as $\\dfrac{\\purpleC1}{100}$.", "Add the two parts together.\n\n $\\dfrac{\\blueD1}{10} + \\dfrac{\\purpleC1}{100}$", "$\\begin{align}\n&= \\dfrac{\\blueD10}{100} + \\dfrac{\\purpleC1}{100} \\\\\\\\\n&= \\dfrac{\\blueD1\\purpleC1}{100}\n\\end{align}$\n\n[[☃ explanation 1]]\n"], "widget_types": ["numeric-input"], "answer_data": {"numeric-input 1": {"type": "numeric-input", "answers": [{"answerForms": ["proper"], "maxError": 0, "message": "", "simplify": "optional", "status": "correct", "strict": true, "value": 0.11}]}}}, {"item_id": "8b3d7410995d5733afd3f739fa7a540f", "question_content": "**Express $0.15$ as a fraction.**\n\n[[☃ numeric-input 1]]", "hints": ["Let's look at $0.15$ on a place value table.\n\nOnes |. | Tenths | Hundredths\n:-: | :-: | :-: | :-:  \n$0$ | .| $\\blueD1$ | $\\purpleC5$", "The number $\\blueD1$ is in the tenths place, so we have one tenth.\n\nOne tenth can be written as $\\dfrac{\\blueD1}{10}$.", "The number $\\purpleC5$ is in the hundredths place, so we have five hundredths.\n\nFive hundredths can be written as $\\dfrac{\\purpleC5}{100}$.", "Add the two parts together.\n\n $\\dfrac{\\blueD1}{10} + \\dfrac{\\purpleC5}{100}$", "$\\begin{align}\n=& \\dfrac{\\blueD10}{100} + \\dfrac{\\purpleC5}{100}\\\\\\\\\n=& \\dfrac{\\blueD1\\purpleC5}{100}\n\\end{align}$\n\n\n[[☃ explanation 1]]"], "widget_types": ["numeric-input"], "answer_data": {"numeric-input 1": {"type": "numeric-input", "answers": [{"answerForms": ["proper"], "maxError": 0, "message": "", "simplify": "optional", "status": "correct", "strict": true, "value": 0.15}]}}}, {"item_id": "86f848cc91af50898486302eeeed41d2", "question_content": "**Express $0.19$ as a fraction.**\n\n[[☃ numeric-input 1]]", "hints": ["Let's look at $0.19$ on a place value table.\n\nOnes |. | Tenths | Hundredths\n:-: | :-: | :-: | :-:  \n$0$ | .| $\\blueD1$ | $\\purpleC9$", "The number $\\blueD1$ is in the tenths place, so we have one tenth.\n\nOne tenth can be written as $\\dfrac{\\blueD1}{10}$.", "The number $\\purpleC9$ is in the hundredths place, so we have nine hundredths.\n\nNine hundredths can be written as $\\dfrac{\\purpleC9}{100}$.", "Add the two parts together.\n\n $\\dfrac{\\blueD1}{10} + \\dfrac{\\purpleC9}{100}$", "$\\begin{align}\n=& \\dfrac{\\blueD10}{100} + \\dfrac{\\purpleC9}{100}\\\\\\\\\n=& \\dfrac{\\blueD1\\purpleC9}{100}\n\\end{align}$\n\n\n[[☃ explanation 1]]"], "widget_types": ["numeric-input"], "answer_data": {"numeric-input 1": {"type": "numeric-input", "answers": [{"answerForms": ["proper"], "maxError": 0, "message": "", "simplify": "optional", "status": "correct", "strict": true, "value": 0.19}]}}}, {"item_id": "02211b9e55e85f5bb652c2f74cece699", "question_content": "**Express $0.24$ as a fraction.**\n\n[[☃ numeric-input 1]]", "hints": ["Let's look at $0.24$ on a place value table.\n\nOnes |. | Tenths | Hundredths\n:-: | :-: | :-: | :-:  \n$0$ | .| $\\blueD2$ | $\\purpleC4$", "The number $\\blueD2$ is in the tenths place, so we have two tenths.\n\nTwo tenths can be written as $\\dfrac{\\blueD2}{10}$.", "The number $\\purpleC4$ is in the hundredths place, so we have four hundredths.\n\nFour hundredths can be written as $\\dfrac{\\purpleC4}{100}$.", "Add the two parts together.\n\n $\\dfrac{\\blueD2}{10} + \\dfrac{\\purpleC4}{100}$", "$\\begin{align}\n=& \\dfrac{\\blueD20}{100} + \\dfrac{\\purpleC4}{100}\\\\\\\\\n=& \\dfrac{\\blueD2\\purpleC4}{100}\n\\end{align}$\n\n\n[[☃ explanation 1]]"], "widget_types": ["numeric-input"], "answer_data": {"numeric-input 1": {"type": "numeric-input", "answers": [{"answerForms": ["proper"], "maxError": 0, "message": "", "simplify": "optional", "status": "correct", "strict": true, "value": 0.24}]}}}, {"item_id": "11386f5d6b745a3b8e0afad3af8613a6", "question_content": "**Express $0.29$ as a fraction.**\n\n[[☃ numeric-input 1]]", "hints": ["Let's look at $0.29$ on a place value table.\n\nOnes |. | Tenths | Hundredths\n:-: | :-: | :-: | :-:  \n$0$ | .| $\\blueD2$ | $\\purpleC9$", "The number $\\blueD2$ is in the tenths place, so we have two tenths.\n\nTwo tenths can be written as $\\dfrac{\\blueD2}{10}$.", "The number $\\purpleC9$ is in the hundredths place, so we have nine hundredths.\n\nNine hundredths can be written as $\\dfrac{\\purpleC9}{100}$.", "Add the two parts together.\n\n $\\dfrac{\\blueD2}{10} + \\dfrac{\\purpleC9}{100}$", "$\\begin{align}\n=& \\dfrac{\\blueD20}{100} + \\dfrac{\\purpleC9}{100}\\\\\\\\\n=& \\dfrac{\\blueD2\\purpleC9}{100}\n\\end{align}$\n\n\n[[☃ explanation 1]]"], "widget_types": ["numeric-input"], "answer_data": {"numeric-input 1": {"type": "numeric-input", "answers": [{"answerForms": ["proper"], "maxError": 0, "message": "", "simplify": "optional", "status": "correct", "strict": true, "value": 0.29}]}}}, {"item_id": "9980378d91eb5069891468eba93a3ea5", "question_content": "**Express $0.38$ as a fraction.**\n\n[[☃ numeric-input 1]]", "hints": ["Let's look at $0.38$ on a place value table.\n\nOnes |. | Tenths | Hundredths\n:-: | :-: | :-: | :-:  \n$0$ | .| $\\blueD3$ | $\\purpleC8$", "The number $\\blueD3$ is in the tenths place, so we have three tenths.\n\nThree tenths can be written as $\\dfrac{\\blueD3}{10}$.", "The number $\\purpleC8$ is in the hundredths place, so we have eight hundredths.\n\nEight hundredths can be written as $\\dfrac{\\purpleC8}{100}$.", "Add the two parts together.\n\n $\\dfrac{\\blueD3}{10} + \\dfrac{\\purpleC8}{100}$", "$\\begin{align}\n=& \\dfrac{\\blueD30}{100} + \\dfrac{\\purpleC8}{100}\\\\\\\\\n=& \\dfrac{\\blueD3\\purpleC8}{100}\n\\end{align}$\n\n\n[[☃ explanation 1]]"], "widget_types": ["numeric-input"], "answer_data": {"numeric-input 1": {"type": "numeric-input", "answers": [{"answerForms": ["proper"], "maxError": 0, "message": "", "simplify": "optional", "status": "correct", "strict": true, "value": 0.38}]}}}, {"item_id": "368607ed4b045eef9d442acfc946e6ad", "question_content": "**Express $0.46$ as a fraction.**\n\n[[☃ numeric-input 1]]", "hints": ["Let's look at $0.46$ on a place value table.\n\nOnes |. | Tenths | Hundredths\n:-: | :-: | :-: | :-:  \n$0$ | .| $\\blueD4$ | $\\purpleC6$", "The number $\\blueD4$ is in the tenths place, so we have four tenths.\n\nFour tenths can be written as $\\dfrac{\\blueD4}{10}$.", "The number $\\purpleC6$ is in the hundredths place, so we have six hundredths. \n\nSix hundredths can be written as $\\dfrac{\\purpleC6}{100}$.", "Add the two parts together.\n\n $\\dfrac{\\blueD4}{10} + \\dfrac{\\purpleC6}{100}$", "$\\begin{align}\n=& \\dfrac{\\blueD40}{100} + \\dfrac{\\purpleC6}{100}\\\\\\\\\n=& \\dfrac{\\blueD4\\purpleC6}{100}\n\\end{align}$\n\n\n[[☃ explanation 1]]"], "widget_types": ["numeric-input"], "answer_data": {"numeric-input 1": {"type": "numeric-input", "answers": [{"answerForms": ["proper"], "maxError": 0, "message": "", "simplify": "optional", "status": "correct", "strict": true, "value": 0.46}]}}}, {"item_id": "1cd841ba96f85817bf672f6ba12d3b48", "question_content": "**Express $0.53$ as a fraction.**\n\n[[☃ numeric-input 1]]", "hints": ["Let's look at $0.53$ on a place value table.\n\nOnes |. | Tenths | Hundredths\n:-: | :-: | :-: | :-:  \n$0$ | .| $\\blueD5$ | $\\purpleC3$", "The number $\\blueD5$ is in the tenths place, so we have five tenths.\n\nFive tenths can be written as $\\dfrac{\\blueD5}{10}$.", "The number $\\purpleC3$ is in the hundredths place, so we have three hundredths.\n\nThree hundredths can be written as $\\dfrac{\\purpleC3}{100}$.", "Add the two parts together.\n\n $\\dfrac{\\blueD5}{10} + \\dfrac{\\purpleC3}{100}$", "$\\begin{align}\n=& \\dfrac{\\blueD50}{100} + \\dfrac{\\purpleC3}{100}\\\\\\\\\n=& \\dfrac{\\blueD5\\purpleC3}{100}\n\\end{align}$\n\n\n[[☃ explanation 1]]"], "widget_types": ["numeric-input"], "answer_data": {"numeric-input 1": {"type": "numeric-input", "answers": [{"answerForms": ["proper"], "maxError": 0, "message": "", "simplify": "optional", "status": "correct", "strict": true, "value": 0.53}]}}}, {"item_id": "baf96bc1a56b5a4f9f75e606a432be17", "question_content": "**Express $0.58$ as a fraction.**\n\n[[☃ numeric-input 1]]", "hints": ["Let's look at $0.58$ on a place value table.\n\nOnes |. | Tenths | Hundredths\n:-: | :-: | :-: | :-:  \n$0$ | .| $\\blueD5$ | $\\purpleC8$", "The number $\\blueD5$ is in the tenths place, so we have five tenths.\n\nFive tenths can be written as $\\dfrac{\\blueD5}{10}$.", "The number $\\purpleC8$ is in the hundredths place, so we have eight hundredths.\n\nEight hundredths can be written as $\\dfrac{\\purpleC8}{100}$.", "Add the two parts together.\n\n $\\dfrac{\\blueD5}{10} + \\dfrac{\\purpleC8}{100}$", "$\\begin{align}\n=& \\dfrac{\\blueD50}{100} + \\dfrac{\\purpleC8}{100}\\\\\\\\\n=& \\dfrac{\\blueD5\\purpleC8}{100}\n\\end{align}$\n\n\n[[☃ explanation 1]]"], "widget_types": ["numeric-input"], "answer_data": {"numeric-input 1": {"type": "numeric-input", "answers": [{"answerForms": ["proper"], "maxError": 0, "message": "", "simplify": "optional", "status": "correct", "strict": true, "value": 0.58}]}}}, {"item_id": "a3096e60e74552a1a1d58602c9714c88", "question_content": "**Express $0.63$ as a fraction.**\n\n[[☃ numeric-input 1]]", "hints": ["Let's look at $0.63$ on a place value table.\n\nOnes |. | Tenths | Hundredths\n:-: | :-: | :-: | :-:  \n$0$ | .| $\\blueD6$ | $\\purpleC3$", "The number $\\blueD6$ is in the tenths place, so we have six tenths.\n\nSix tenths can be written as $\\dfrac{\\blueD6}{10}$.", "The number $\\purpleC3$ is in the hundredths place, so we have three hundredths.\n\nThree hundredths can be written as $\\dfrac{\\purpleC3}{100}$.", "Add the two parts together.\n\n $\\dfrac{\\blueD6}{10} + \\dfrac{\\purpleC3}{100}$", "$\\begin{align}\n=& \\dfrac{\\blueD60}{100} + \\dfrac{\\purpleC3}{100}\\\\\\\\\n=& \\dfrac{\\blueD6\\purpleC3}{100}\n\\end{align}$\n\n\n[[☃ explanation 1]]"], "widget_types": ["numeric-input"], "answer_data": {"numeric-input 1": {"type": "numeric-input", "answers": [{"answerForms": ["proper"], "maxError": 0, "message": "", "simplify": "optional", "status": "correct", "strict": true, "value": 0.63}]}}}, {"item_id": "2f8e1b758c1f51839d23e591d72b7992", "question_content": "**Express $0.78$ as a fraction.**\n\n[[☃ numeric-input 1]]", "hints": ["Let's look at $0.78$ on a place value table.\n\nOnes |. | Tenths | Hundredths\n:-: | :-: | :-: | :-:  \n$0$ | .| $\\blueD7$ | $\\purpleC8$", "The number $\\blueD7$ is in the tenths place, so we have seven tenths.\n\nSeven tenths can be written as $\\dfrac{\\blueD7}{10}$.", "The number $\\purpleC8$ is in the hundredths place, so we have eight hundredths.\n\nEight hundredths can be written as $\\dfrac{\\purpleC8}{100}$.", "Add the two parts together.\n\n $\\dfrac{\\blueD7}{10} + \\dfrac{\\purpleC8}{100}$", "$\\begin{align}\n=& \\dfrac{\\blueD70}{100} + \\dfrac{\\purpleC8}{100}\\\\\\\\\n=& \\dfrac{\\blueD7\\purpleC8}{100}\n\\end{align}$\n\n\n[[☃ explanation 1]]"], "widget_types": ["numeric-input"], "answer_data": {"numeric-input 1": {"type": "numeric-input", "answers": [{"answerForms": ["proper"], "maxError": 0, "message": "", "simplify": "optional", "status": "correct", "strict": true, "value": 0.78}]}}}, {"item_id": "d72fa9ee856457c8b85a38d3cb6b7b4a", "question_content": "**Express $0.82$ as a fraction.**\n\n[[☃ numeric-input 1]]", "hints": ["Let's look at $0.82$ on a place value table.\n\nOnes |. | Tenths | Hundredths\n:-: | :-: | :-: | :-:  \n$0$ | .| $\\blueD8$ | $\\purpleC2$", "The number $\\blueD8$ is in the tenths place, so we have eight tenths.\n\nEight tenths can be written as $\\dfrac{\\blueD8}{10}$.", "The number $\\purpleC2$ is in the hundredths place, so we have two hundredths.\n\nTwo hundredths can be written as $\\dfrac{\\purpleC2}{100}$.", "Add the two parts together.\n\n $\\dfrac{\\blueD8}{10} + \\dfrac{\\purpleC2}{100}$", "$\\begin{align}\n=& \\dfrac{\\blueD80}{100} + \\dfrac{\\purpleC2}{100}\\\\\\\\\n=& \\dfrac{\\blueD8\\purpleC2}{100}\n\\end{align}$\n\n\n[[☃ explanation 1]]"], "widget_types": ["numeric-input"], "answer_data": {"numeric-input 1": {"type": "numeric-input", "answers": [{"answerForms": ["proper"], "maxError": 0, "message": "", "simplify": "optional", "status": "correct", "strict": true, "value": 0.82}]}}}, {"item_id": "c594435eb2d85254a1a301cf38291c36", "question_content": "**Express $0.96$ as a fraction.**\n\n[[☃ numeric-input 1]]", "hints": ["Let's look at $0.96$ on a place value table.\n\nOnes |. | Tenths | Hundredths\n:-: | :-: | :-: | :-:  \n$0$ | .| $\\blueD9$ | $\\purpleC6$", "The number $\\blueD9$ is in the tenths place, so we have nine tenths.\n\nNine tenths can be written as $\\dfrac{\\blueD9}{10}$.", "The number $\\purpleC6$ is in the hundredths place, so we have six hundredths.\n\nSix hundredths can be written as $\\dfrac{\\purpleC6}{100}$.", "Add the two parts together.\n\n $\\dfrac{\\blueD9}{10} + \\dfrac{\\purpleC6}{100}$", "$\\begin{align}\n=& \\dfrac{\\blueD90}{100} + \\dfrac{\\purpleC6}{100}\\\\\\\\\n=& \\dfrac{\\blueD9\\purpleC6}{100}\n\\end{align}$\n\n\n[[☃ explanation 1]]"], "widget_types": ["numeric-input"], "answer_data": {"numeric-input 1": {"type": "numeric-input", "answers": [{"answerForms": ["proper"], "maxError": 0, "message": "", "simplify": "optional", "status": "correct", "strict": true, "value": 0.96}]}}}], "mastery_model": {"type": "m_of_n", "m": 5, "n": 7}, "randomize": true}